setup.cfg
setup.py
ToLedger.egg-info/PKG-INFO
ToLedger.egg-info/SOURCES.txt
ToLedger.egg-info/dependency_links.txt
ToLedger.egg-info/requires.txt
ToLedger.egg-info/top_level.txt
toledger/bankstatements.py
toledger/toledger.py