Metadata-Version: 1.1
Name: ToLedger
Version: 1.0
Summary: Convert bank statements to Ledger
Home-page: https://github.com/bartbroere/toledger/
Author: Bart Broere
Author-email: mail@bartbroere.eu
License: MIT
Keywords: ledger,convert,conversion,bank,ing,nl,accounting,command,commandline,cli
Platform: UNKNOWN
Classifier: Development Status :: 5 - Production/Stable
Classifier: License :: OSI Approved :: MIT License
Classifier: Programming Language :: Python
Classifier: Programming Language :: Python :: 3
Classifier: Programming Language :: Python :: 3.2
Classifier: Programming Language :: Python :: 3.3
Classifier: Programming Language :: Python :: 3.4
Classifier: Programming Language :: Python :: 3.5
Classifier: Programming Language :: Python :: 3.6
Classifier: Topic :: Office/Business :: Financial
Classifier: Topic :: Utilities
